{"events":[{"params":[1],"time":8347.82608695652,"name":"Camera Movement"},{"params":[0,true,4,"CLASSIC","In"],"name":"Camera Movement","time":16695.652173913},{"params":[0],"name":"Camera Movement","time":21913.0434782609},{"params":[1],"time":25043.4782608696,"name":"Camera Movement"},{"params":[0],"time":27130.4347826087,"name":"Camera Movement"},{"params":[1],"time":29217.3913043478,"name":"Camera Movement"},{"params":[0],"time":31304.347826087,"name":"Camera Movement"},{"params":[],"time":33391.3043478261,"name":"songCard"},{"params":[0,true,4,"CLASSIC","In"],"name":"Camera Movement","time":39652.1739130435},{"params":["0.9","Equals"],"name":"Zoom","time":39652.1739130435},{"params":[0,true,4,"CLASSIC","In"],"time":40173.9130434783,"name":"Camera Movement"},{"params":["0.7","Equals"],"name":"Zoom","time":40173.9130434783},{"params":[0,true,4,"CLASSIC","In"],"time":40695.652173913,"name":"Camera Movement"},{"params":["0.9","Equals"],"name":"Zoom","time":40695.652173913},{"params":[1,true,4,"CLASSIC","In"],"name":"Camera Movement","time":41739.1304347826},{"params":["0.7","Equals"],"name":"Zoom","time":41739.1304347826},{"params":[1,true,4,"CLASSIC","In"],"time":48000,"name":"Camera Movement"},{"params":["0.9","Equals"],"name":"Zoom","time":48000},{"params":[1,true,4,"CLASSIC","In"],"name":"Camera Movement","time":48521.7391304348},{"params":["0.7","Equals"],"time":48521.7391304348,"name":"Zoom"},{"params":[1,true,4,"CLASSIC","In"],"name":"Camera Movement","time":49043.4782608696},{"params":["0.9","Equals"],"time":49043.4782608696,"name":"Zoom"},{"params":[250,200,true,50,"quad","InOut",false],"time":50086.9565217391,"name":"Camera Position"},{"params":[true,0.7,"camGame",50,"quad","InOut","direct",true],"time":50086.9565217391,"name":"Camera Zoom"},{"params":[0,true,50,"quad","InOut"],"name":"Camera Movement","time":58434.7826086956},{"params":[true,1,"camGame",4,"quart","InOut","direct",true],"name":"Camera Zoom","time":58434.7826086956},{"params":[1,true,4,"CLASSIC","In"],"time":64695.652173913,"name":"Camera Movement"},{"params":[0,true,4,"CLASSIC","In"],"name":"Camera Movement","time":65739.1304347826},{"params":[1],"time":75130.4347826087,"name":"Camera Movement"},{"params":[0,false,4,"CLASSIC","In"],"time":83478.2608695652,"name":"Camera Movement"},{"params":[false,1.2,"camGame",4,"quad","InOut","direct",true],"time":83478.2608695652,"name":"Camera Zoom"},{"params":[true,1,"camGame",4,"quart","InOut","direct",false],"time":84521.7391304348,"name":"Camera Zoom"},{"params":[true,1.2,"camGame",4,"quart","InOut","direct",false],"time":85565.2173913044,"name":"Camera Zoom"},{"params":[1,false,4,"CLASSIC","In"],"name":"Camera Movement","time":85565.2173913044},{"params":[true,1,"camGame",4,"quart","InOut","direct",false],"name":"Camera Zoom","time":86608.6956521739},{"params":[0,false,4,"CLASSIC","In"],"name":"Camera Movement","time":87652.1739130435},{"params":[true,1.2,"camGame",4,"quart","InOut","direct",true],"name":"Camera Zoom","time":87652.1739130435},{"params":[true,1,"camGame",4,"quart","InOut","direct",false],"name":"Camera Zoom","time":88695.652173913},{"params":[true,1.2,"camGame",4,"quart","InOut","direct",false],"name":"Camera Zoom","time":89739.1304347826},{"params":[1,false,4,"CLASSIC","In"],"time":89739.1304347826,"name":"Camera Movement"},{"params":[true,1,"camGame",4,"quart","InOut","direct",false],"time":90652.1739130435,"name":"Camera Zoom"},{"params":[0,true,4,"CLASSIC","In"],"time":91826.0869565217,"name":"Camera Movement"},{"params":[true,0.8,"camGame",4,"quart","InOut","direct",true],"time":91826.0869565217,"name":"Camera Zoom"},{"params":[1],"time":93913.0434782609,"name":"Camera Movement"},{"params":[260,250,true,4,"CLASSIC","In",false],"time":96000,"name":"Camera Position"},{"params":[true,0.9,"camGame",4,"linear","In","direct",true],"time":96000,"name":"Camera Zoom"},{"params":[1,true,4,"CLASSIC","In"],"time":99130.4347826087,"name":"Camera Movement"},{"params":[true,1.5,"camGame",4,"quad","InOut","direct",true],"time":99130.4347826087,"name":"Camera Zoom"},{"params":[0,true,4,"CLASSIC","In"],"time":100173.913043478,"name":"Camera Movement"},{"params":["0.7","Equals"],"time":100173.913043478,"name":"Zoom"},{"params":[0,true,4,"CLASSIC","In"],"time":106434.782608696,"name":"Camera Movement"},{"params":["0.9","Equals"],"time":106434.782608696,"name":"Zoom"},{"params":[0,true,4,"CLASSIC","In"],"name":"Camera Movement","time":106956.52173913},{"params":["0.7","Equals"],"time":106956.52173913,"name":"Zoom"},{"params":[0,true,4,"CLASSIC","In"],"name":"Camera Movement","time":107478.260869565},{"params":["0.9","Equals"],"time":107478.260869565,"name":"Zoom"},{"params":[1,true,4,"CLASSIC","In"],"time":108521.739130435,"name":"Camera Movement"},{"params":["0.7","Equals"],"time":108521.739130435,"name":"Zoom"},{"params":[1,true,4,"CLASSIC","In"],"name":"Camera Movement","time":114782.608695652},{"params":["0.9","Equals"],"time":114782.608695652,"name":"Zoom"},{"params":[1,true,4,"CLASSIC","In"],"time":115304.347826087,"name":"Camera Movement"},{"params":["0.7","Equals"],"name":"Zoom","time":115304.347826087},{"params":[1,true,4,"CLASSIC","In"],"time":115826.086956522,"name":"Camera Movement"},{"params":["0.9","Equals"],"name":"Zoom","time":115826.086956522},{"params":[250,200,true,50,"quad","InOut",false],"name":"Camera Position","time":116869.565217391},{"params":[true,0.7,"camGame",50,"quad","InOut","direct",true],"name":"Camera Zoom","time":116869.565217391},{"params":[0,true,50,"quad","InOut"],"time":125217.391304348,"name":"Camera Movement"},{"params":[true,1,"camGame",4,"quart","InOut","direct",true],"time":125217.391304348,"name":"Camera Zoom"},{"params":[1,true,4,"CLASSIC","In"],"name":"Camera Movement","time":131478.260869565},{"params":[0,true,4,"CLASSIC","In"],"time":132521.739130435,"name":"Camera Movement"},{"params":[0,true,4,"CLASSIC","In"],"time":132521.739130435,"name":"Camera Movement"},{"params":[1],"name":"Camera Movement","time":135652.173913043},{"params":[0],"name":"Camera Movement","time":137739.130434783},{"params":[1],"name":"Camera Movement","time":139826.086956522},{"params":[0],"name":"Camera Movement","time":141913.043478261}]}